durin/Profiler.py
durin/Read_profilers.py
durin/__init__.py
durin/__main__.py
durin/actuator.py
durin/cli.py
durin/durin.py
durin/durin_birdseye.jpg
durin/dvs.py
durin/sensor.py
durin/ui.py
durin/controller/__init__.py
durin/controller/dvs.py
durin/controller/server.py
durin/controller/test/__init__.py
durin/controller/test/test_stream.py
durin/examples/CPU_test.py
durin/examples/__init__.py
durin/examples/braitenberg.py
durin/examples/commands.py
durin/examples/dashboard.py
durin/examples/main.py
durin/examples/plot.py
durin/examples/record.py
durin/examples/stats.py
durin/io/__init__.py
durin/io/command.py
durin/io/gamepad.py
durin/io/network.py
durin/io/ringbuffer.py
durin/io/runnable.py
durin/io/schema.capnp
durin-0.0.84.data/scripts/durin
durin-0.0.84.dist-info/METADATA
durin-0.0.84.dist-info/WHEEL
durin-0.0.84.dist-info/top_level.txt
durin-0.0.84.dist-info/RECORD
