Metadata-Version: 2.1
Name: durin
Version: 0.0.84
Summary: Python control interface for the Durin robot
Maintainer: Jens E. Pedersen
Maintainer-email: jeped@kth.se
License: LGPLv3
Requires-Dist: inputs
Requires-Dist: numpy
Requires-Dist: pycapnp
Requires-Dist: pyusb
Requires-Dist: pygame
Provides-Extra: aestream
Requires-Dist: aestream ; extra == 'aestream'
